haystack_integrations/components/evaluators/py.typed
haystack_integrations/components/evaluators/deepeval/__init__.py
haystack_integrations/components/evaluators/deepeval/evaluator.py
haystack_integrations/components/evaluators/deepeval/metrics.py
deepeval_haystack-0.3.0.dist-info/METADATA
deepeval_haystack-0.3.0.dist-info/WHEEL
deepeval_haystack-0.3.0.dist-info/licenses/LICENSE.txt
deepeval_haystack-0.3.0.dist-info/RECORD
